jmail/__init__.py
jmail/util.py
jmail-0.1.dist-info/DESCRIPTION.rst
jmail-0.1.dist-info/entry_points.txt
jmail-0.1.dist-info/METADATA
jmail-0.1.dist-info/metadata.json
jmail-0.1.dist-info/pbr.json
jmail-0.1.dist-info/RECORD
jmail-0.1.dist-info/top_level.txt
jmail-0.1.dist-info/WHEEL
