Metadata-Version: 2.0
Name: jmail
Version: 0.1
Summary: Simple mail lib4u
Home-page: https://github.com/jiajie999/jmail
Author: jiajie999
Author-email: jiajie999@gmail.com
License: MIT
Platform: UNKNOWN
Requires-Dist: click
Requires-Dist: colorama
